{"data":{"site":{"siteMetadata":{"data":{"title":"Fagseminar høst 2018","schedules":[{"day":"Torsdag 4. April","collections":[{"time":"20:20","title":"Flyet drar fra Stavanger Lufthavn","titleS":null,"link":null},{"time":"21:30","title":"Vi ankommer København","titleS":null,"link":null}]},{"day":"Fredag 5. April","collections":[{"time":"09:00","title":"Kubernetes Cluster Bring-Up","titleS":"1. Sjekkliste: Veien til bedre nettsider (UX)","link":"https://github.com/GoogleCloudPlatform/kubernetes-workshops/blob/master/bring-up/cloud.md"},{"time":"09:45 - 10:00","title":"Pause","titleS":null,"link":null},{"time":"10:00","title":"Kubernetes Core Concepts Workshops","titleS":"2. Sjekkliste: Søkemotoroptimaliseringstips (Innohold)","link":"https://github.com/GoogleCloudPlatform/kubernetes-workshops/tree/master/core-concepts"},{"time":"10:45","title":" ","titleS":"Pause","link":null},{"time":"11:00","title":" ","titleS":"3. Webanalyse og innsikt med Google Analytics + egen trening","link":null},{"time":"12:00","title":"Lunsj","titleS":null,"link":null},{"time":"13:00","title":" ","titleS":"Hvordan fungerer remarkering?","link":null},{"time":"14:15","title":" ","titleS":"Pause","link":null},{"time":"14:15","title":" ","titleS":"Inbound marketing med MailChimp","link":null},{"time":"15:00","title":" ","titleS":"Pause","link":null},{"time":"15:15","title":" ","titleS":"Annonsering med Bing Ads","link":null},{"time":"16:00","title":"Workshop ferdig","titleS":"Oppsummerende refleksjoner og diskusjon av muligheter for mer salg  under middagen","link":null},{"time":"18:00","title":"Middag på Vækst","titleS":null,"link":null}]},{"day":"Lørdag 6. April","collections":[{"time":"12:00","title":"Lunsj på Øl og Brød","titleS":null,"link":null},{"time":"14:00-16:00","title":"Sykkeltur","titleS":null,"link":null},{"time":"19:00","title":"Middag på Warpigs","titleS":null,"link":null}]},{"day":"Søndag 7. April","collections":[{"time":"16:40","title":"Flyet drar fra København","titleS":null,"link":null},{"time":"17:50","title":"Vi ankommer Stavanger Lufthavn","titleS":null,"link":null}]}]}}}}}